{"version":1,"name":"acid-kaleido","params":{
 "layer.0.generator":{"type":"int","value":3},"layer.0.opacity":{"type":"float","value":1.0},"layer.0.warp":{"type":"float","value":0.4},"layer.0.scale":{"type":"float","value":1.2},
 "layer.1.generator":{"type":"int","value":24},"layer.1.opacity":{"type":"float","value":0.4},"layer.1.blend":{"type":"int","value":1},
 "post.mirror.enable":{"type":"bool","value":true},"post.mirror.mode":{"type":"int","value":3},
 "post.hue.enable":{"type":"bool","value":true},"post.hue.rate":{"type":"float","value":0.05},
 "post.bloom.enable":{"type":"bool","value":true},"post.bloom.amount":{"type":"float","value":0.55}
},"mappings":[],"mod_routes":[
 {"source":"audio.mid","target":"layer.0.warp","amount":0.5,"smooth":0.2},
 {"source":"lfo.2","target":"layer.0.p1","amount":0.4,"smooth":0.0},
 {"source":"audio.low","target":"layer.1.opacity","amount":0.5,"smooth":0.1},
 {"source":"lfo.4","target":"layer.0.rotate","amount":0.3,"smooth":0.0}
],"text":[]}
